
<Group_Fitness_Classes>
<Fitness_Class Class='Aerobox'/>
<Fitness_Class Class='AquaFit'/>
<Fitness_Class Class='Barre Blast'/>
<Fitness_Class Class='Barre Bootcamp'/>
<Fitness_Class Class='FYI: Barre Bootcamp is a barefoot fitness class so be prepared to work in your barefeet or grippy "yoga" socks.'/>
<Fitness_Class Class='Bellyfit Flow'/>
<Fitness_Class Class='Body Strong'/>
<Fitness_Class Class='Box/Strength'/>
<Fitness_Class Class='Cardio Strength'/>
<Fitness_Class Class='Core Conditioning'/>
<Fitness_Class Class='DanceFit'/>
<Fitness_Class Class='Group Force'/>
<Fitness_Class Class='Happy Hour'/>
<Fitness_Class Class='Interval Workout'/>
<Fitness_Class Class='Member Yoga'/>
<Fitness_Class Class='Older Adult Strength Training'/>
<Fitness_Class Class='Older Adult Yoga'/>
<Fitness_Class Class='Pound'/>
<Fitness_Class Class='Strength Circuit'/>
<Fitness_Class Class='Spin'/>
<Fitness_Class Class='Step'/>
<Fitness_Class Class='Strong By Zumba'/>
<Fitness_Class Class='Zumba ®'/>
<Fitness_Class Class='Zumba Step'/>
</Group_Fitness_Classes>